audiosnatch/__init__.py
audiosnatch/__main__.py
audiosnatch/ipaudio.py
audiosnatch-0.3.2.dist-info/METADATA
audiosnatch-0.3.2.dist-info/WHEEL
audiosnatch-0.3.2.dist-info/entry_points.txt
audiosnatch-0.3.2.dist-info/licenses/LICENSE
audiosnatch-0.3.2.dist-info/RECORD
