Metadata-Version: 2.4
Name: audiosnatch
Version: 0.3.2
Summary: An Audiobook downloader for goldenaudiobooks and sharedaudiobooks.
Project-URL: Homepage, https://github.com/rozari0/AudioSnatchCLI
Project-URL: Bug Tracker, https://github.com/rozari0/AudioSnatchCLI/issues
Author-email: rozari0 <rozario@duck.com>
License-File: LICENSE
Requires-Python: >=3.8
Requires-Dist: beautifulsoup4>=4.12.3
Requires-Dist: lxml>=5.2.2
Requires-Dist: pypdl>=1.5.6
Requires-Dist: requests>=2.32.3
Requires-Dist: rich-click>=1.8.3
Requires-Dist: validators>=0.33.0
